cuellartensorflow/__init__.py
cuellartensorflow-1.0.3.dist-info/METADATA
cuellartensorflow-1.0.3.dist-info/WHEEL
cuellartensorflow-1.0.3.dist-info/licenses/LICENSE
cuellartensorflow-1.0.3.dist-info/RECORD
