Metadata-Version: 2.1
Name: cuellartensorflow
Version: 1.0.3
Summary: Una libreria simple para crear modelos de lenguaje con tensorflow
Project-URL: Homepage, https://github.com/pypa/sampleproject
Project-URL: Bug Tracker, https://github.com/pypa/sampleproject/issues
Author-email: Emiliano Cuellar <ec446162@gmail.com>
License-File: LICENSE
Classifier: License :: OSI Approved :: MIT License
Classifier: Operating System :: OS Independent
Classifier: Programming Language :: Python :: 3
Requires-Python: >=3.6
Requires-Dist: numpy
Requires-Dist: pickle5
Requires-Dist: tensorflow
Requires-Dist: tqdm
Requires-Dist: wikipedia
